CoreEase/__init__.py
CoreEase/compiler.py
CoreEase/executor.py
CoreEase/explorer.py
CoreEase/output.py
CoreEase/system.py
CoreEase/timemanager.py
CoreEase/webdriver.py
CoreEase/_compiler/_LEXER.py
CoreEase/_compiler/_PARSER.py
CoreEase/_compiler/_PIPELINE_exe.py
CoreEase/_compiler/__init__.py
CoreEase/_output/_CMD_centered.py
CoreEase/_output/_CMD_normal.py
CoreEase/_output/_CMD_properties.py
CoreEase/_output/_WINDOWS_messagebox.py
CoreEase/_output/__init__.py
CoreEase/_system/_CMD.py
CoreEase/_system/_DIR.py
CoreEase/_system/_ENV_variables.py
CoreEase/_system/_FILE.py
CoreEase/_system/_PATH.py
CoreEase/_system/_RESTART.py
CoreEase/_system/_SHUTDOWN.py
CoreEase/_system/_TIME.py
CoreEase/_system/__init__.py
CoreEase/_threadpool/_SUBMIT_no_buffer.py
CoreEase/_threadpool/_SUBMIT_with_buffer.py
CoreEase/_threadpool/_SUBMIT_with_buffer_no_animation.py
CoreEase/_threadpool/_THREAD_pool_init.py
CoreEase/_threadpool/__init__.py
CoreEase/_webdriver/_HTML_parser.py
CoreEase/_webdriver/_TOOLS_advanced.py
CoreEase/_webdriver/_TOOLS_simple.py
CoreEase/_webdriver/_WEBDRIVER_base.py
CoreEase/_webdriver/_WEBDRIVER_init.py
CoreEase/_webdriver/__init__.py
CoreEase-0.3.6.dist-info/LICENSE
CoreEase-0.3.6.dist-info/METADATA
CoreEase-0.3.6.dist-info/WHEEL
CoreEase-0.3.6.dist-info/top_level.txt
CoreEase-0.3.6.dist-info/RECORD
