Metadata-Version: 2.2
Name: CoreEase
Version: 0.3.6
Summary: A Python package to standardize my workflows and simplify repetitive tasks.
Home-page: https://github.com/Casbian/CoreEase
Author: Casbian
Classifier: Programming Language :: Python :: 3
Classifier: License :: OSI Approved :: MIT License
Classifier: Operating System :: OS Independent
Requires-Python: >=3.7
License-File: LICENSE
Requires-Dist: selenium>=4.0.0
Requires-Dist: nuitka>=1.0.0
Dynamic: author
Dynamic: classifier
Dynamic: description
Dynamic: description-content-type
Dynamic: home-page
Dynamic: requires-dist
Dynamic: requires-python
Dynamic: summary
